siaw/__init__.py
siaw/say_it_another_way.py
siaw/utils/__init__.py
siaw/utils/antonym/__init__.py
siaw/utils/antonym/antonym.py
siaw/utils/antonym/dict_antonym.txt
siaw/utils/chaizi/__init__.py
siaw/utils/chaizi/chaizi-ft.txt
siaw/utils/chaizi/chaizi-jt.txt
siaw/utils/chaizi/chaizi.py
siaw/utils/homophone/__init__.py
siaw/utils/homophone/chinese_homophone_char.txt
siaw/utils/homophone/chinese_homophone_word.txt
siaw/utils/homophone/homophone.py
siaw/utils/synonym/__init__.py
siaw/utils/synonym/dict_synonym.txt
siaw/utils/synonym/synonym.py
siaw/utils/textfilter/__init__.py
siaw/utils/textfilter/filter.py
siaw/utils/textfilter/keywords.txt
siaw-0.0.2.data/data/README.md
tests/__init__.py
tests/test_say_it_another_way.py
siaw-0.0.2.dist-info/LICENSE
siaw-0.0.2.dist-info/METADATA
siaw-0.0.2.dist-info/WHEEL
siaw-0.0.2.dist-info/top_level.txt
siaw-0.0.2.dist-info/RECORD
